qpp/__init__.py
qpp/__main__.py
qpp/config.py
qpp/console.py
qpp/metadata.py
qpp/queries.py
qpp/renderables.py
qpp-0.3.1.dist-info/entry_points.txt
qpp-0.3.1.dist-info/LICENSE
qpp-0.3.1.dist-info/WHEEL
qpp-0.3.1.dist-info/METADATA
qpp-0.3.1.dist-info/RECORD
