Metadata-Version: 2.1
Name: qpp
Version: 0.3.1
Summary: Query PyPI, ask it anything.
Keywords: pypi,query,search,find
Author-email: Ralf Luetkemeier <foss@rlue.de>
Requires-Python: >=3.9,<4
Classifier: Development Status :: 4 - Beta
Classifier: Environment :: Console
Classifier: Intended Audience :: Developers
Classifier: License :: OSI Approved :: MIT License
Classifier: Operating System :: MacOS
Classifier: Operating System :: Microsoft :: Windows
Classifier: Operating System :: POSIX :: Linux
Classifier: Programming Language :: Python :: 3
Classifier: Programming Language :: Python :: 3.9
Classifier: Programming Language :: Python :: 3.10
Classifier: Programming Language :: Python :: 3.11
Classifier: Programming Language :: Python :: 3.12
Classifier: Programming Language :: Python :: 3 :: Only
Classifier: Topic :: Software Development
Classifier: Topic :: Utilities
Requires-Dist: beautifulsoup4 >= 4.11.0
Requires-Dist: requests >= 2.28.0
Requires-Dist: rich >=12.0.0
Requires-Dist: rich-argparse-plus >= 0.3.0
Requires-Dist: rich_rst >= 1.0.0
Requires-Dist: tomli >= 2.0.0; python_version < '3.11'
Requires-Dist: flake8 ; extra == "dev"
Requires-Dist: flit ; extra == "dev"
Requires-Dist: pylint ; extra == "dev"
Requires-Dist: pytest ; extra == "dev"
Requires-Dist: pytest-cov ; extra == "dev"
Requires-Dist: tox ; extra == "dev"
Requires-Dist: pytest >=7.2.0 ; extra == "test"
Requires-Dist: pytest-cov ; extra == "test"
Provides-Extra: dev
Provides-Extra: test
